{
    "asset": {
        "format": "jpg",
        "id": "76ce064279b494ba99b6d75a1c80fbfd",
        "name": "Cheque309066.jpg",
        "path": "file:/home/bhanu/Documents/bank_cheques/bank_cheque_data/images/Cheque309066.jpg",
        "size": {
            "width": 2365,
            "height": 1079
        },
        "state": 2,
        "type": 1
    },
    "regions": [
        {
            "id": "GgFBLAC0M",
            "type": "RECTANGLE",
            "tags": [
                "bank"
            ],
            "boundingBox": {
                "height": 79.98895899053628,
                "width": 425.35971223021585,
                "left": 236.5,
                "top": 30.793621845425868
            },
            "points": [
                {
                    "x": 236.5,
                    "y": 30.793621845425868
                },
                {
                    "x": 661.8597122302159,
                    "y": 30.793621845425868
                },
                {
                    "x": 661.8597122302159,
                    "y": 110.78258083596215
                },
                {
                    "x": 236.5,
                    "y": 110.78258083596215
                }
            ]
        },
        {
            "id": "GZOQtJzhS",
            "type": "RECTANGLE",
            "tags": [
                "date"
            ],
            "boundingBox": {
                "height": 85.09463722397477,
                "width": 495.11870503597123,
                "left": 1801.8237410071943,
                "top": 81.85040417981072
            },
            "points": [
                {
                    "x": 1801.8237410071943,
                    "y": 81.85040417981072
                },
                {
                    "x": 2296.9424460431655,
                    "y": 81.85040417981072
                },
                {
                    "x": 2296.9424460431655,
                    "y": 166.9450414037855
                },
                {
                    "x": 1801.8237410071943,
                    "y": 166.9450414037855
                }
            ]
        },
        {
            "id": "kPLxXGPvG",
            "type": "RECTANGLE",
            "tags": [
                "ifsc"
            ],
            "boundingBox": {
                "height": 35.7397476340694,
                "width": 272.23021582733816,
                "left": 262.021582733813,
                "top": 139.71475749211356
            },
            "points": [
                {
                    "x": 262.021582733813,
                    "y": 139.71475749211356
                },
                {
                    "x": 534.2517985611511,
                    "y": 139.71475749211356
                },
                {
                    "x": 534.2517985611511,
                    "y": 175.45450512618297
                },
                {
                    "x": 262.021582733813,
                    "y": 175.45450512618297
                }
            ]
        },
        {
            "id": "SzMJzFn2N",
            "type": "RECTANGLE",
            "tags": [
                "payee"
            ],
            "boundingBox": {
                "height": 97.00788643533123,
                "width": 850.7194244604317,
                "left": 343.6906474820144,
                "top": 207.79046727129338
            },
            "points": [
                {
                    "x": 343.6906474820144,
                    "y": 207.79046727129338
                },
                {
                    "x": 1194.4100719424462,
                    "y": 207.79046727129338
                },
                {
                    "x": 1194.4100719424462,
                    "y": 304.7983537066246
                },
                {
                    "x": 343.6906474820144,
                    "y": 304.7983537066246
                }
            ]
        },
        {
            "id": "G7w1bdPrR",
            "type": "RECTANGLE",
            "tags": [
                "amount_number"
            ],
            "boundingBox": {
                "height": 90.20031545741325,
                "width": 415.15107913669067,
                "left": 1810.3309352517986,
                "top": 417.1232748422713
            },
            "points": [
                {
                    "x": 1810.3309352517986,
                    "y": 417.1232748422713
                },
                {
                    "x": 2225.4820143884895,
                    "y": 417.1232748422713
                },
                {
                    "x": 2225.4820143884895,
                    "y": 507.32359029968455
                },
                {
                    "x": 1810.3309352517986,
                    "y": 507.32359029968455
                }
            ]
        },
        {
            "id": "BRMzzxjN5",
            "type": "RECTANGLE",
            "tags": [
                "amount_words"
            ],
            "boundingBox": {
                "height": 200.82334384858046,
                "width": 2237.3920863309354,
                "left": 68.05755395683454,
                "top": 311.60592468454263
            },
            "points": [
                {
                    "x": 68.05755395683454,
                    "y": 311.60592468454263
                },
                {
                    "x": 2305.44964028777,
                    "y": 311.60592468454263
                },
                {
                    "x": 2305.44964028777,
                    "y": 512.429268533123
                },
                {
                    "x": 68.05755395683454,
                    "y": 512.429268533123
                }
            ]
        },
        {
            "id": "zXrhXJGCG",
            "type": "RECTANGLE",
            "tags": [
                "acc_num"
            ],
            "boundingBox": {
                "height": 54.46056782334385,
                "width": 364.10791366906477,
                "left": 364.10791366906477,
                "top": 536.255766955836
            },
            "points": [
                {
                    "x": 364.10791366906477,
                    "y": 536.255766955836
                },
                {
                    "x": 728.2158273381295,
                    "y": 536.255766955836
                },
                {
                    "x": 728.2158273381295,
                    "y": 590.7163347791799
                },
                {
                    "x": 364.10791366906477,
                    "y": 590.7163347791799
                }
            ]
        },
        {
            "id": "rurcdtjlE",
            "type": "RECTANGLE",
            "tags": [
                "sign"
            ],
            "boundingBox": {
                "height": 95.30599369085174,
                "width": 234.79856115107916,
                "left": 2068.94964028777,
                "top": 723.4639688485805
            },
            "points": [
                {
                    "x": 2068.94964028777,
                    "y": 723.4639688485805
                },
                {
                    "x": 2303.748201438849,
                    "y": 723.4639688485805
                },
                {
                    "x": 2303.748201438849,
                    "y": 818.7699625394322
                },
                {
                    "x": 2068.94964028777,
                    "y": 818.7699625394322
                }
            ]
        },
        {
            "id": "xo5SremEk",
            "type": "RECTANGLE",
            "tags": [
                "micr"
            ],
            "boundingBox": {
                "height": 85.09463722397477,
                "width": 1179.0971223021584,
                "left": 568.2805755395684,
                "top": 954.9213820977918
            },
            "points": [
                {
                    "x": 568.2805755395684,
                    "y": 954.9213820977918
                },
                {
                    "x": 1747.3776978417268,
                    "y": 954.9213820977918
                },
                {
                    "x": 1747.3776978417268,
                    "y": 1040.0160193217666
                },
                {
                    "x": 568.2805755395684,
                    "y": 1040.0160193217666
                }
            ]
        }
    ],
    "version": "2.1.0"
}