{
    "asset": {
        "format": "jpg",
        "id": "ae6fb0c2f07483545706c2045ad7ec5c",
        "name": "Cheque309115.jpg",
        "path": "file:/home/bhanu/Documents/bank_cheques/bank_cheque_data/images/Cheque309115.jpg",
        "size": {
            "width": 2365,
            "height": 1100
        },
        "state": 2,
        "type": 1
    },
    "regions": [
        {
            "id": "knMYCE7rh",
            "type": "RECTANGLE",
            "tags": [
                "bank"
            ],
            "boundingBox": {
                "height": 76.50695517774342,
                "width": 411.7482014388489,
                "left": 248.41007194244605,
                "top": 36.15484930448223
            },
            "points": [
                {
                    "x": 248.41007194244605,
                    "y": 36.15484930448223
                },
                {
                    "x": 660.158273381295,
                    "y": 36.15484930448223
                },
                {
                    "x": 660.158273381295,
                    "y": 112.66180448222565
                },
                {
                    "x": 248.41007194244605,
                    "y": 112.66180448222565
                }
            ]
        },
        {
            "id": "h-z5HjayL",
            "type": "RECTANGLE",
            "tags": [
                "ifsc"
            ],
            "boundingBox": {
                "height": 40.80370942812983,
                "width": 284.1402877697842,
                "left": 248.41007194244605,
                "top": 146.66489567233384
            },
            "points": [
                {
                    "x": 248.41007194244605,
                    "y": 146.66489567233384
                },
                {
                    "x": 532.5503597122303,
                    "y": 146.66489567233384
                },
                {
                    "x": 532.5503597122303,
                    "y": 187.46860510046366
                },
                {
                    "x": 248.41007194244605,
                    "y": 187.46860510046366
                }
            ]
        },
        {
            "id": "rAtsl6tg0",
            "type": "RECTANGLE",
            "tags": [
                "date"
            ],
            "boundingBox": {
                "height": 86.25627897990726,
                "width": 513.8345323741007,
                "left": 1786.5107913669065,
                "top": 88.85964064914992
            },
            "points": [
                {
                    "x": 1786.5107913669065,
                    "y": 88.85964064914992
                },
                {
                    "x": 2300.345323741007,
                    "y": 88.85964064914992
                },
                {
                    "x": 2300.345323741007,
                    "y": 175.11591962905717
                },
                {
                    "x": 1786.5107913669065,
                    "y": 175.11591962905717
                }
            ]
        },
        {
            "id": "qU5tlqS2i",
            "type": "RECTANGLE",
            "tags": [
                "payee"
            ],
            "boundingBox": {
                "height": 115.61051004636785,
                "width": 1155.2769784172663,
                "left": 195.66546762589928,
                "top": 201.06984157650695
            },
            "points": [
                {
                    "x": 195.66546762589928,
                    "y": 201.06984157650695
                },
                {
                    "x": 1350.9424460431655,
                    "y": 201.06984157650695
                },
                {
                    "x": 1350.9424460431655,
                    "y": 316.6803516228748
                },
                {
                    "x": 195.66546762589928,
                    "y": 316.6803516228748
                }
            ]
        },
        {
            "id": "x9AUzFE2_",
            "type": "RECTANGLE",
            "tags": [
                "amount_number"
            ],
            "boundingBox": {
                "height": 102.00927357032457,
                "width": 484.91007194244605,
                "left": 1762.6906474820146,
                "top": 416.98947063369394
            },
            "points": [
                {
                    "x": 1762.6906474820146,
                    "y": 416.98947063369394
                },
                {
                    "x": 2247.6007194244607,
                    "y": 416.98947063369394
                },
                {
                    "x": 2247.6007194244607,
                    "y": 518.9987442040185
                },
                {
                    "x": 1762.6906474820146,
                    "y": 518.9987442040185
                }
            ]
        },
        {
            "id": "XXYZa1fnz",
            "type": "RECTANGLE",
            "tags": [
                "amount_words"
            ],
            "boundingBox": {
                "height": 212.0677163833076,
                "width": 2222.0791366906474,
                "left": 69.7589928057554,
                "top": 323.4809698608964
            },
            "points": [
                {
                    "x": 69.7589928057554,
                    "y": 323.4809698608964
                },
                {
                    "x": 2291.838129496403,
                    "y": 323.4809698608964
                },
                {
                    "x": 2291.838129496403,
                    "y": 535.548686244204
                },
                {
                    "x": 69.7589928057554,
                    "y": 535.548686244204
                }
            ]
        },
        {
            "id": "vUkGX6B6o",
            "type": "RECTANGLE",
            "tags": [
                "acc_num"
            ],
            "boundingBox": {
                "height": 51.00463678516228,
                "width": 333.48201438848923,
                "left": 362.4064748201439,
                "top": 547.9013717156105
            },
            "points": [
                {
                    "x": 362.4064748201439,
                    "y": 547.9013717156105
                },
                {
                    "x": 695.8884892086331,
                    "y": 547.9013717156105
                },
                {
                    "x": 695.8884892086331,
                    "y": 598.9060085007727
                },
                {
                    "x": 362.4064748201439,
                    "y": 598.9060085007727
                }
            ]
        },
        {
            "id": "Nk9dan3bi",
            "type": "RECTANGLE",
            "tags": [
                "sign"
            ],
            "boundingBox": {
                "height": 248.2225656877898,
                "width": 357.30215827338134,
                "left": 1929.431654676259,
                "top": 566.60307187017
            },
            "points": [
                {
                    "x": 1929.431654676259,
                    "y": 566.60307187017
                },
                {
                    "x": 2286.73381294964,
                    "y": 566.60307187017
                },
                {
                    "x": 2286.73381294964,
                    "y": 814.8256375579598
                },
                {
                    "x": 1929.431654676259,
                    "y": 814.8256375579598
                }
            ]
        },
        {
            "id": "1HRNOKQjQ",
            "type": "RECTANGLE",
            "tags": [
                "micr"
            ],
            "boundingBox": {
                "height": 96.90880989180835,
                "width": 1187.6043165467627,
                "left": 569.9820143884892,
                "top": 945.7375386398763
            },
            "points": [
                {
                    "x": 569.9820143884892,
                    "y": 945.7375386398763
                },
                {
                    "x": 1757.586330935252,
                    "y": 945.7375386398763
                },
                {
                    "x": 1757.586330935252,
                    "y": 1042.6463485316847
                },
                {
                    "x": 569.9820143884892,
                    "y": 1042.6463485316847
                }
            ]
        }
    ],
    "version": "2.1.0"
}