{
    "asset": {
        "format": "jpg",
        "id": "d627b6e5ed90fa0590417ccecf0cecaa",
        "name": "Cheque309127.jpg",
        "path": "file:/home/bhanu/Documents/bank_cheques/bank_cheque_data/images/Cheque309127.jpg",
        "size": {
            "width": 2365,
            "height": 1079
        },
        "state": 2,
        "type": 1
    },
    "regions": [
        {
            "id": "yJKWx5tCm",
            "type": "RECTANGLE",
            "tags": [
                "bank"
            ],
            "boundingBox": {
                "height": 69.77760252365931,
                "width": 440.67266187050365,
                "left": 238.20143884892087,
                "top": 41.00497831230284
            },
            "points": [
                {
                    "x": 238.20143884892087,
                    "y": 41.00497831230284
                },
                {
                    "x": 678.8741007194245,
                    "y": 41.00497831230284
                },
                {
                    "x": 678.8741007194245,
                    "y": 110.78258083596215
                },
                {
                    "x": 238.20143884892087,
                    "y": 110.78258083596215
                }
            ]
        },
        {
            "id": "Sa1B1YYdj",
            "type": "RECTANGLE",
            "tags": [
                "ifsc"
            ],
            "boundingBox": {
                "height": 40.845425867507885,
                "width": 268.8273381294964,
                "left": 260.3201438848921,
                "top": 160.13747042586752
            },
            "points": [
                {
                    "x": 260.3201438848921,
                    "y": 160.13747042586752
                },
                {
                    "x": 529.1474820143885,
                    "y": 160.13747042586752
                },
                {
                    "x": 529.1474820143885,
                    "y": 200.9828962933754
                },
                {
                    "x": 260.3201438848921,
                    "y": 200.9828962933754
                }
            ]
        },
        {
            "id": "V56FKU-9v",
            "type": "RECTANGLE",
            "tags": [
                "date"
            ],
            "boundingBox": {
                "height": 62.97003154574133,
                "width": 476.40287769784175,
                "left": 1795.0179856115108,
                "top": 103.97500985804417
            },
            "points": [
                {
                    "x": 1795.0179856115108,
                    "y": 103.97500985804417
                },
                {
                    "x": 2271.4208633093526,
                    "y": 103.97500985804417
                },
                {
                    "x": 2271.4208633093526,
                    "y": 166.9450414037855
                },
                {
                    "x": 1795.0179856115108,
                    "y": 166.9450414037855
                }
            ]
        },
        {
            "id": "Q67fJXwds",
            "type": "RECTANGLE",
            "tags": [
                "payee"
            ],
            "boundingBox": {
                "height": 105.51735015772871,
                "width": 775.8561151079138,
                "left": 455.9856115107914,
                "top": 214.59803824921136
            },
            "points": [
                {
                    "x": 455.9856115107914,
                    "y": 214.59803824921136
                },
                {
                    "x": 1231.841726618705,
                    "y": 214.59803824921136
                },
                {
                    "x": 1231.841726618705,
                    "y": 320.1153884069401
                },
                {
                    "x": 455.9856115107914,
                    "y": 320.1153884069401
                }
            ]
        },
        {
            "id": "Q50x5mD7x",
            "type": "RECTANGLE",
            "tags": [
                "amount_number"
            ],
            "boundingBox": {
                "height": 100.41167192429023,
                "width": 529.1474820143885,
                "left": 1749.0791366906476,
                "top": 415.4213820977918
            },
            "points": [
                {
                    "x": 1749.0791366906476,
                    "y": 415.4213820977918
                },
                {
                    "x": 2278.226618705036,
                    "y": 415.4213820977918
                },
                {
                    "x": 2278.226618705036,
                    "y": 515.833054022082
                },
                {
                    "x": 1749.0791366906476,
                    "y": 515.833054022082
                }
            ]
        },
        {
            "id": "wmFZnx8QV",
            "type": "RECTANGLE",
            "tags": [
                "amount_words"
            ],
            "boundingBox": {
                "height": 185.506309148265,
                "width": 2227.18345323741,
                "left": 54.44604316546763,
                "top": 332.02863761829656
            },
            "points": [
                {
                    "x": 54.44604316546763,
                    "y": 332.02863761829656
                },
                {
                    "x": 2281.629496402878,
                    "y": 332.02863761829656
                },
                {
                    "x": 2281.629496402878,
                    "y": 517.5349467665616
                },
                {
                    "x": 54.44604316546763,
                    "y": 517.5349467665616
                }
            ]
        },
        {
            "id": "uKQNb8ycj",
            "type": "RECTANGLE",
            "tags": [
                "acc_num"
            ],
            "boundingBox": {
                "height": 73.1813880126183,
                "width": 464.4928057553957,
                "left": 304.55755395683457,
                "top": 543.0633379337539
            },
            "points": [
                {
                    "x": 304.55755395683457,
                    "y": 543.0633379337539
                },
                {
                    "x": 769.0503597122303,
                    "y": 543.0633379337539
                },
                {
                    "x": 769.0503597122303,
                    "y": 616.2447259463722
                },
                {
                    "x": 304.55755395683457,
                    "y": 616.2447259463722
                }
            ]
        },
        {
            "id": "i8_7EOW35",
            "type": "RECTANGLE",
            "tags": [
                "sign"
            ],
            "boundingBox": {
                "height": 180.4006309148265,
                "width": 226.29136690647482,
                "left": 2051.9352517985612,
                "top": 623.0522969242902
            },
            "points": [
                {
                    "x": 2051.9352517985612,
                    "y": 623.0522969242902
                },
                {
                    "x": 2278.226618705036,
                    "y": 623.0522969242902
                },
                {
                    "x": 2278.226618705036,
                    "y": 803.4529278391168
                },
                {
                    "x": 2051.9352517985612,
                    "y": 803.4529278391168
                }
            ]
        },
        {
            "id": "eDX9XWgoI",
            "type": "RECTANGLE",
            "tags": [
                "micr"
            ],
            "boundingBox": {
                "height": 103.81545741324922,
                "width": 1167.1870503597122,
                "left": 575.0863309352518,
                "top": 951.5175966088328
            },
            "points": [
                {
                    "x": 575.0863309352518,
                    "y": 951.5175966088328
                },
                {
                    "x": 1742.273381294964,
                    "y": 951.5175966088328
                },
                {
                    "x": 1742.273381294964,
                    "y": 1055.333054022082
                },
                {
                    "x": 575.0863309352518,
                    "y": 1055.333054022082
                }
            ]
        }
    ],
    "version": "2.1.0"
}